{"head":{"title":"CSS antialiasing","category":"CSS","layout":"2017/sheet","updated":"2017-10-13T00:00:00.000Z","intro":"Here's a 4-line snippet on how to get beautiful, antialiased text with CSS.\n"},"body":[{"title":"Antialias","elms":"{: .-prime}\n\n```css\n* {\n  -webkit-font-smoothing: antialiased;\n  -moz-osx-font-smoothing: grayscale;\n}\n```\n","h2":null},{"title":"Support","elms":"\n * Firefox 25+ on OSX\n * Webkits (Chrome, Safari, etc)\n","h2":null},{"title":null,"elms":"{: .-one-column}\n\n * [maxvoltar.com](http://maxvoltar.com/archive/-webkit-font-smoothing)\n * [maximilianhoffman.com](http://maximilianhoffmann.com/posts/better-font-rendering-on-osx)\n * [ilikekillnerds.com](http://ilikekillnerds.com/2010/12/a-solution-to-stop-font-face-fonts-looking-bold-on-mac-browsers/)\n{: .-also-see}","h2":"References"}]}