{"head":{"title":"Cron","category":"CLI","layout":"2017/sheet","updated":"2018-05-03T00:00:00.000Z","weight":-3},"body":[{"title":null,"elms":"{: .-two-column}\n","h2":"Format"},{"title":"Format","elms":"\n```\nMin  Hour Day  Mon  Weekday\n```\n{: .-setup}\n\n```\n*    *    *    *    *  command to be executed\n```\n\n```\n┬    ┬    ┬    ┬    ┬\n│    │    │    │    └─  Weekday  (0=Sun .. 6=Sat)\n│    │    │    └──────  Month    (1..12)\n│    │    └───────────  Day      (1..31)\n│    └────────────────  Hour     (0..23)\n└─────────────────────  Minute   (0..59)\n```\n{: .-setup.-box-chars}\n","h2":"Format"},{"title":"Operators","elms":"\n| Operator | Description                |\n| ---      | ---                        |\n| `*`      | all values                 |\n| `,`      | separate individual values |\n| `-`      | a range of values          |\n| `/`      | divide a value into steps  |\n","h2":"Format"},{"title":"Examples","elms":"\n| Example        | Description                 |\n| ---            | ---                         |\n| `0 * * * *`    | every hour                  |\n| `*/15 * * * *` | every 15 mins               |\n| `0 */2 * * *`  | every 2 hours               |\n| `0 18 * * 0-6` | every week Mon-Sat at 6pm   |\n| `10 2 * * 6,7` | every Sat and Thu on 2:10am |\n| `0 0 * * 0`    | every Sunday midnight       |\n| ---            | ---                         |\n| `@reboot`      | every reboot                |\n","h2":"Format"},{"title":"Crontab","elms":"\n```bash\n# Adding tasks easily\necho \"@reboot echo hi\" | crontab\n```\n\n```bash\n# Open in editor\ncrontab -e\n```\n\n```bash\n# List tasks\ncrontab -l [-u user]\n```","h2":"Format"}]}