{"head":{"title":"Share links","layout":"2017/sheet","category":"HTML","updated":"2017-09-04T00:00:00.000Z"},"body":[{"title":null,"elms":"{: .-one-column}\n\nFacebook:\n{:.-setup}\n\n```html\n<a href='https://www.facebook.com/sharer/sharer.php?u=URL' target='share'>\n```\n\nTwitter:\n{:.-setup}\n\n```html\n<a href='https://twitter.com/intent/tweet?text=DESCRIPTION+URL' target='share'>\n```\n\nGoogle Plus:\n{:.-setup}\n\n```html\n<a href='https://plus.google.com/share?url=URL' target='share'>\n```","h2":"Share links"}]}